fair_kmeans/__init__.py
fair_kmeans/fair_kmeans.py
fair_kmeans_uchicago-0.1.3.dist-info/METADATA
fair_kmeans_uchicago-0.1.3.dist-info/WHEEL
fair_kmeans_uchicago-0.1.3.dist-info/top_level.txt
fair_kmeans_uchicago-0.1.3.dist-info/RECORD
